<annotation>
	<folder>tmp</folder>
	<filename>077c3a0b-1a3a-4801-910a-593cae7dbdd7.jpg</filename>
	<path>images/all/077c3a0b-1a3a-4801-910a-593cae7dbdd7.jpg</path>
	<source>
		<database>Unknown</database>
	</source>
	<size>
		<width>500</width>
		<height>375</height>
		<depth>3</depth>
	</size>
	<segmented>0</segmented>
	<object>
		<name>Brown_Rat</name>
		<pose>Unspecified</pose>
		<truncated>0</truncated>
		<difficult>0</difficult>
		<bndbox>
			<xmin>149</xmin>
			<ymin>100</ymin>
			<xmax>345</xmax>
			<ymax>265</ymax>
		</bndbox>
	</object>
</annotation>
