<annotation>
	<folder>tmp</folder>
	<filename>107374da-eae0-4273-84a1-f6ce8f85f602.jpg</filename>
	<path>images/training/107374da-eae0-4273-84a1-f6ce8f85f602.jpg</path>
	<source>
		<database>Unknown</database>
	</source>
	<size>
		<width>500</width>
		<height>375</height>
		<depth>3</depth>
	</size>
	<segmented>0</segmented>
	<object>
		<name>Grey_Heron</name>
		<pose>Unspecified</pose>
		<truncated>0</truncated>
		<difficult>0</difficult>
		<bndbox>
			<xmin>144</xmin>
			<ymin>51</ymin>
			<xmax>348</xmax>
			<ymax>294</ymax>
		</bndbox>
	</object>
</annotation>
