<annotation>
	<folder>tmp</folder>
	<filename>2023_02_06_15:36:22.1461552967.jpg</filename>
	<path>images/all/2023_02_06_15:36:22.1461552967.jpg</path>
	<source>
		<database>Unknown</database>
	</source>
	<size>
		<width>1024</width>
		<height>576</height>
		<depth>3</depth>
	</size>
	<segmented>0</segmented>
	<object>
		<name>Eurasian_Collared_Dove</name>
		<pose>Unspecified</pose>
		<truncated>0</truncated>
		<difficult>0</difficult>
		<bndbox>
			<xmin>32</xmin>
			<ymin>262</ymin>
			<xmax>190</xmax>
			<ymax>357</ymax>
		</bndbox>
	</object>
	<object>
		<name>Eurasian_Collared_Dove</name>
		<pose>Unspecified</pose>
		<truncated>0</truncated>
		<difficult>0</difficult>
		<bndbox>
			<xmin>537</xmin>
			<ymin>234</ymin>
			<xmax>612</xmax>
			<ymax>288</ymax>
		</bndbox>
	</object>
</annotation>
