<annotation>
	<folder>tmp</folder>
	<filename>41201bad-d553-49de-9854-6d2ac9ad7759.jpg</filename>
	<path>images/training/41201bad-d553-49de-9854-6d2ac9ad7759.jpg</path>
	<source>
		<database>Unknown</database>
	</source>
	<size>
		<width>500</width>
		<height>230</height>
		<depth>3</depth>
	</size>
	<segmented>0</segmented>
	<object>
		<name>Domestic_Cat</name>
		<pose>Unspecified</pose>
		<truncated>0</truncated>
		<difficult>0</difficult>
		<bndbox>
			<xmin>278</xmin>
			<ymin>67</ymin>
			<xmax>423</xmax>
			<ymax>145</ymax>
		</bndbox>
	</object>
	<object>
		<name>Domestic_Cat</name>
		<pose>Unspecified</pose>
		<truncated>0</truncated>
		<difficult>0</difficult>
		<bndbox>
			<xmin>20</xmin>
			<ymin>67</ymin>
			<xmax>274</xmax>
			<ymax>148</ymax>
		</bndbox>
	</object>
</annotation>
