<annotation>
	<folder>tmp</folder>
	<filename>48dbd58d-09c7-4706-a231-f9f95e8c78ad.jpg</filename>
	<path>images/training/48dbd58d-09c7-4706-a231-f9f95e8c78ad.jpg</path>
	<source>
		<database>Unknown</database>
	</source>
	<size>
		<width>375</width>
		<height>500</height>
		<depth>3</depth>
	</size>
	<segmented>0</segmented>
	<object>
		<name>Eastern_Gray_Squirrel</name>
		<pose>Unspecified</pose>
		<truncated>0</truncated>
		<difficult>0</difficult>
		<bndbox>
			<xmin>133</xmin>
			<ymin>160</ymin>
			<xmax>224</xmax>
			<ymax>490</ymax>
		</bndbox>
	</object>
</annotation>
