<annotation>
	<folder>tmp</folder>
	<filename>492ca63b-4341-44f4-bb43-0dfd9ab53083.jpg</filename>
	<path>images/training/492ca63b-4341-44f4-bb43-0dfd9ab53083.jpg</path>
	<source>
		<database>Unknown</database>
	</source>
	<size>
		<width>333</width>
		<height>500</height>
		<depth>3</depth>
	</size>
	<segmented>0</segmented>
	<object>
		<name>Great_Tit</name>
		<pose>Unspecified</pose>
		<truncated>0</truncated>
		<difficult>0</difficult>
		<bndbox>
			<xmin>15</xmin>
			<ymin>105</ymin>
			<xmax>323</xmax>
			<ymax>452</ymax>
		</bndbox>
	</object>
</annotation>
