<annotation>
	<folder>tmp</folder>
	<filename>6ac78ccf-b601-409b-8eef-3dcc88c9a83a.jpg</filename>
	<path>images/training/6ac78ccf-b601-409b-8eef-3dcc88c9a83a.jpg</path>
	<source>
		<database>Unknown</database>
	</source>
	<size>
		<width>500</width>
		<height>375</height>
		<depth>3</depth>
	</size>
	<segmented>0</segmented>
	<object>
		<name>Red_Fox</name>
		<pose>Unspecified</pose>
		<truncated>0</truncated>
		<difficult>0</difficult>
		<bndbox>
			<xmin>289</xmin>
			<ymin>152</ymin>
			<xmax>307</xmax>
			<ymax>176</ymax>
		</bndbox>
	</object>
</annotation>
