<annotation>
	<folder>tmp</folder>
	<filename>736d7194-6f9c-4162-85a3-110024eb312e.jpg</filename>
	<path>images/all/736d7194-6f9c-4162-85a3-110024eb312e.jpg</path>
	<source>
		<database>Unknown</database>
	</source>
	<size>
		<width>500</width>
		<height>375</height>
		<depth>3</depth>
	</size>
	<segmented>0</segmented>
	<object>
		<name>Common_Dandelion</name>
		<pose>Unspecified</pose>
		<truncated>0</truncated>
		<difficult>0</difficult>
		<bndbox>
			<xmin>151</xmin>
			<ymin>94</ymin>
			<xmax>334</xmax>
			<ymax>260</ymax>
		</bndbox>
	</object>
</annotation>
