<annotation>
	<folder>tmp</folder>
	<filename>835c648e-f771-4901-987e-46d809dd77b6.jpg</filename>
	<path>images/training/835c648e-f771-4901-987e-46d809dd77b6.jpg</path>
	<source>
		<database>Unknown</database>
	</source>
	<size>
		<width>500</width>
		<height>479</height>
		<depth>3</depth>
	</size>
	<segmented>0</segmented>
	<object>
		<name>Blue_Tit</name>
		<pose>Unspecified</pose>
		<truncated>0</truncated>
		<difficult>0</difficult>
		<bndbox>
			<xmin>185</xmin>
			<ymin>252</ymin>
			<xmax>291</xmax>
			<ymax>338</ymax>
		</bndbox>
	</object>
</annotation>
