<annotation>
	<folder>tmp</folder>
	<filename>83a6ca35-d57d-4a1f-8195-f68b363d5702.jpg</filename>
	<path>images/training/83a6ca35-d57d-4a1f-8195-f68b363d5702.jpg</path>
	<source>
		<database>Unknown</database>
	</source>
	<size>
		<width>375</width>
		<height>500</height>
		<depth>3</depth>
	</size>
	<segmented>0</segmented>
	<object>
		<name>Wood_Pigeon</name>
		<pose>Unspecified</pose>
		<truncated>0</truncated>
		<difficult>0</difficult>
		<bndbox>
			<xmin>174</xmin>
			<ymin>235</ymin>
			<xmax>190</xmax>
			<ymax>259</ymax>
		</bndbox>
	</object>
</annotation>
