<annotation>
	<folder>tmp</folder>
	<filename>8c810a61-0c40-474a-9736-01c1e901d2ac.jpg</filename>
	<path>images/all/8c810a61-0c40-474a-9736-01c1e901d2ac.jpg</path>
	<source>
		<database>Unknown</database>
	</source>
	<size>
		<width>500</width>
		<height>375</height>
		<depth>3</depth>
	</size>
	<segmented>0</segmented>
	<object>
		<name>Brown_Rat</name>
		<pose>Unspecified</pose>
		<truncated>1</truncated>
		<difficult>0</difficult>
		<bndbox>
			<xmin>127</xmin>
			<ymin>127</ymin>
			<xmax>500</xmax>
			<ymax>250</ymax>
		</bndbox>
	</object>
</annotation>
