<annotation>
	<folder>tmp</folder>
	<filename>93497cfe-bd2e-464f-b181-7df78a5f8dd3.jpg</filename>
	<path>images/training/93497cfe-bd2e-464f-b181-7df78a5f8dd3.jpg</path>
	<source>
		<database>Unknown</database>
	</source>
	<size>
		<width>500</width>
		<height>375</height>
		<depth>3</depth>
	</size>
	<segmented>0</segmented>
	<object>
		<name>Red_Kite</name>
		<pose>Unspecified</pose>
		<truncated>0</truncated>
		<difficult>0</difficult>
		<bndbox>
			<xmin>277</xmin>
			<ymin>94</ymin>
			<xmax>386</xmax>
			<ymax>269</ymax>
		</bndbox>
	</object>
</annotation>
