<annotation>
	<folder>tmp</folder>
	<filename>964a2c50-5107-4caf-be59-771231871c96.jpg</filename>
	<path>images/training/964a2c50-5107-4caf-be59-771231871c96.jpg</path>
	<source>
		<database>Unknown</database>
	</source>
	<size>
		<width>500</width>
		<height>375</height>
		<depth>3</depth>
	</size>
	<segmented>0</segmented>
	<object>
		<name>Eurasian_Goldfinch</name>
		<pose>Unspecified</pose>
		<truncated>0</truncated>
		<difficult>0</difficult>
		<bndbox>
			<xmin>353</xmin>
			<ymin>77</ymin>
			<xmax>458</xmax>
			<ymax>139</ymax>
		</bndbox>
	</object>
	<object>
		<name>Eurasian_Goldfinch</name>
		<pose>Unspecified</pose>
		<truncated>0</truncated>
		<difficult>0</difficult>
		<bndbox>
			<xmin>348</xmin>
			<ymin>227</ymin>
			<xmax>424</xmax>
			<ymax>287</ymax>
		</bndbox>
	</object>
</annotation>
