<annotation>
	<folder>tmp</folder>
	<filename>a7448b37-1e6a-4c6c-89c3-8d196768b4d1.jpg</filename>
	<path>images/training/a7448b37-1e6a-4c6c-89c3-8d196768b4d1.jpg</path>
	<source>
		<database>Unknown</database>
	</source>
	<size>
		<width>500</width>
		<height>375</height>
		<depth>3</depth>
	</size>
	<segmented>0</segmented>
	<object>
		<name>Eurasian_Goldfinch</name>
		<pose>Unspecified</pose>
		<truncated>0</truncated>
		<difficult>0</difficult>
		<bndbox>
			<xmin>216</xmin>
			<ymin>154</ymin>
			<xmax>266</xmax>
			<ymax>210</ymax>
		</bndbox>
	</object>
</annotation>
