<annotation>
	<folder>tmp</folder>
	<filename>a9da2aa1-37c5-4a26-8b33-eecffc335370.jpg</filename>
	<path>images/training/a9da2aa1-37c5-4a26-8b33-eecffc335370.jpg</path>
	<source>
		<database>Unknown</database>
	</source>
	<size>
		<width>500</width>
		<height>375</height>
		<depth>3</depth>
	</size>
	<segmented>0</segmented>
	<object>
		<name>European_Starling</name>
		<pose>Unspecified</pose>
		<truncated>0</truncated>
		<difficult>0</difficult>
		<bndbox>
			<xmin>176</xmin>
			<ymin>107</ymin>
			<xmax>274</xmax>
			<ymax>276</ymax>
		</bndbox>
	</object>
</annotation>
