<annotation>
	<folder>tmp</folder>
	<filename>af700afa-e5d5-4607-aee9-c976f68bea93.jpg</filename>
	<path>images/training/af700afa-e5d5-4607-aee9-c976f68bea93.jpg</path>
	<source>
		<database>Unknown</database>
	</source>
	<size>
		<width>500</width>
		<height>375</height>
		<depth>3</depth>
	</size>
	<segmented>0</segmented>
	<object>
		<name>Grey_Heron</name>
		<pose>Unspecified</pose>
		<truncated>0</truncated>
		<difficult>0</difficult>
		<bndbox>
			<xmin>214</xmin>
			<ymin>91</ymin>
			<xmax>271</xmax>
			<ymax>197</ymax>
		</bndbox>
	</object>
</annotation>
