<annotation>
	<folder>tmp</folder>
	<filename>ba049739-42e4-4d37-b17c-a3547ee20b49.jpg</filename>
	<path>images/all/ba049739-42e4-4d37-b17c-a3547ee20b49.jpg</path>
	<source>
		<database>Unknown</database>
	</source>
	<size>
		<width>500</width>
		<height>375</height>
		<depth>3</depth>
	</size>
	<segmented>0</segmented>
	<object>
		<name>Eurasian_Green_Woodpecker</name>
		<pose>Unspecified</pose>
		<truncated>0</truncated>
		<difficult>1</difficult>
		<bndbox>
			<xmin>135</xmin>
			<ymin>156</ymin>
			<xmax>385</xmax>
			<ymax>214</ymax>
		</bndbox>
	</object>
</annotation>
