<annotation>
	<folder>House Sparrow</folder>
	<filename>ee5b6cad-b51a-4c1c-93a9-9e20e8437234.jpg</filename>
	<path>images/training/ee5b6cad-b51a-4c1c-93a9-9e20e8437234.jpg</path>
	<source>
		<database>Unknown</database>
	</source>
	<size>
		<width>500</width>
		<height>376</height>
		<depth>3</depth>
	</size>
	<segmented>0</segmented>
	<object>
		<name>House_Sparrow</name>
		<pose>Unspecified</pose>
		<truncated>0</truncated>
		<difficult>0</difficult>
		<bndbox>
			<xmin>166</xmin>
			<ymin>118</ymin>
			<xmax>312</xmax>
			<ymax>253</ymax>
		</bndbox>
	</object>
</annotation>
