<annotation>
	<folder>tmp</folder>
	<filename>eebff9a8-971f-403d-bb8d-cdc9074e9379.jpg</filename>
	<path>images/training/eebff9a8-971f-403d-bb8d-cdc9074e9379.jpg</path>
	<source>
		<database>Unknown</database>
	</source>
	<size>
		<width>500</width>
		<height>359</height>
		<depth>3</depth>
	</size>
	<segmented>0</segmented>
	<object>
		<name>Red_Kite</name>
		<pose>Unspecified</pose>
		<truncated>0</truncated>
		<difficult>0</difficult>
		<bndbox>
			<xmin>133</xmin>
			<ymin>45</ymin>
			<xmax>311</xmax>
			<ymax>285</ymax>
		</bndbox>
	</object>
</annotation>
